{
  "Agent_1": {
    "1": {
      "collective": 0,
      "individual": 2,
      "connected": 0,
      "disconnected": 0,
      "giving": 1,
      "taking": 1,
      "mutuality_ratio": 0.25,
      "cooperative_pct": 0.4149377593360996,
      "uncooperative_pct": 1.2448132780082988,
      "total_words": 241
    },
    "2": {
      "collective": 1,
      "individual": 2,
      "connected": 0,
      "disconnected": 0,
      "giving": 3,
      "taking": 1,
      "mutuality_ratio": 1.0,
      "cooperative_pct": 1.6597510373443984,
      "uncooperative_pct": 1.2448132780082988,
      "total_words": 241
    },
    "3": {
      "collective": 0,
      "individual": 1,
      "connected": 0,
      "disconnected": 0,
      "giving": 4,
      "taking": 1,
      "mutuality_ratio": 1.3333333333333333,
      "cooperative_pct": 1.7167381974248928,
      "uncooperative_pct": 0.8583690987124464,
      "total_words": 233
    },
    "4": {
      "collective": 0,
      "individual": 1,
      "connected": 0,
      "disconnected": 0,
      "giving": 2,
      "taking": 5,
      "mutuality_ratio": 0.2857142857142857,
      "cooperative_pct": 0.8771929824561403,
      "uncooperative_pct": 2.631578947368421,
      "total_words": 228
    },
    "5": {
      "collective": 3,
      "individual": 2,
      "connected": 1,
      "disconnected": 0,
      "giving": 3,
      "taking": 2,
      "mutuality_ratio": 1.4,
      "cooperative_pct": 3.1818181818181817,
      "uncooperative_pct": 1.8181818181818181,
      "total_words": 220
    },
    "6": {
      "collective": 0,
      "individual": 1,
      "connected": 0,
      "disconnected": 0,
      "giving": 0,
      "taking": 2,
      "mutuality_ratio": 0.0,
      "cooperative_pct": 0.0,
      "uncooperative_pct": 1.3574660633484164,
      "total_words": 221
    },
    "7": {
      "collective": 0,
      "individual": 0,
      "connected": 0,
      "disconnected": 0,
      "giving": 0,
      "taking": 3,
      "mutuality_ratio": 0.0,
      "cooperative_pct": 0.0,
      "uncooperative_pct": 1.3333333333333335,
      "total_words": 225
    },
    "8": {
      "collective": 0,
      "individual": 0,
      "connected": 0,
      "disconnected": 0,
      "giving": 0,
      "taking": 1,
      "mutuality_ratio": 0.0,
      "cooperative_pct": 0.0,
      "uncooperative_pct": 0.4484304932735426,
      "total_words": 223
    },
    "9": {
      "collective": 0,
      "individual": 0,
      "connected": 0,
      "disconnected": 0,
      "giving": 0,
      "taking": 3,
      "mutuality_ratio": 0.0,
      "cooperative_pct": 0.0,
      "uncooperative_pct": 1.3157894736842104,
      "total_words": 228
    },
    "10": {
      "collective": 0,
      "individual": 0,
      "connected": 0,
      "disconnected": 0,
      "giving": 0,
      "taking": 2,
      "mutuality_ratio": 0.0,
      "cooperative_pct": 0.0,
      "uncooperative_pct": 0.9174311926605505,
      "total_words": 218
    },
    "11": {
      "collective": 0,
      "individual": 1,
      "connected": 0,
      "disconnected": 0,
      "giving": 2,
      "taking": 4,
      "mutuality_ratio": 0.3333333333333333,
      "cooperative_pct": 0.8771929824561403,
      "uncooperative_pct": 2.1929824561403506,
      "total_words": 228
    },
    "12": {
      "collective": 0,
      "individual": 0,
      "connected": 0,
      "disconnected": 0,
      "giving": 1,
      "taking": 1,
      "mutuality_ratio": 0.5,
      "cooperative_pct": 0.4464285714285714,
      "uncooperative_pct": 0.4464285714285714,
      "total_words": 224
    },
    "13": {
      "collective": 0,
      "individual": 1,
      "connected": 0,
      "disconnected": 0,
      "giving": 3,
      "taking": 2,
      "mutuality_ratio": 0.75,
      "cooperative_pct": 1.3157894736842104,
      "uncooperative_pct": 1.3157894736842104,
      "total_words": 228
    },
    "14": {
      "collective": 0,
      "individual": 0,
      "connected": 0,
      "disconnected": 0,
      "giving": 2,
      "taking": 2,
      "mutuality_ratio": 0.6666666666666666,
      "cooperative_pct": 0.8658008658008658,
      "uncooperative_pct": 0.8658008658008658,
      "total_words": 231
    },
    "15": {
      "collective": 0,
      "individual": 1,
      "connected": 0,
      "disconnected": 0,
      "giving": 2,
      "taking": 2,
      "mutuality_ratio": 0.5,
      "cooperative_pct": 0.847457627118644,
      "uncooperative_pct": 1.2711864406779663,
      "total_words": 236
    }
  },
  "Agent_2": {
    "1": {
      "collective": 0,
      "individual": 0,
      "connected": 0,
      "disconnected": 0,
      "giving": 2,
      "taking": 0,
      "mutuality_ratio": 2.0,
      "cooperative_pct": 0.78125,
      "uncooperative_pct": 0.0,
      "total_words": 256
    },
    "2": {
      "collective": 0,
      "individual": 0,
      "connected": 0,
      "disconnected": 0,
      "giving": 1,
      "taking": 1,
      "mutuality_ratio": 0.5,
      "cooperative_pct": 0.5988023952095809,
      "uncooperative_pct": 0.5988023952095809,
      "total_words": 167
    },
    "3": {
      "collective": 0,
      "individual": 0,
      "connected": 0,
      "disconnected": 0,
      "giving": 3,
      "taking": 1,
      "mutuality_ratio": 1.5,
      "cooperative_pct": 1.875,
      "uncooperative_pct": 0.625,
      "total_words": 160
    },
    "4": {
      "collective": 0,
      "individual": 1,
      "connected": 0,
      "disconnected": 0,
      "giving": 0,
      "taking": 1,
      "mutuality_ratio": 0.0,
      "cooperative_pct": 0.0,
      "uncooperative_pct": 1.0810810810810811,
      "total_words": 185
    },
    "5": {
      "collective": 0,
      "individual": 1,
      "connected": 1,
      "disconnected": 0,
      "giving": 0,
      "taking": 2,
      "mutuality_ratio": 0.25,
      "cooperative_pct": 0.4975124378109453,
      "uncooperative_pct": 1.4925373134328357,
      "total_words": 201
    },
    "6": {
      "collective": 1,
      "individual": 0,
      "connected": 0,
      "disconnected": 0,
      "giving": 1,
      "taking": 2,
      "mutuality_ratio": 0.6666666666666666,
      "cooperative_pct": 1.1173184357541899,
      "uncooperative_pct": 1.1173184357541899,
      "total_words": 179
    },
    "7": {
      "collective": 1,
      "individual": 0,
      "connected": 0,
      "disconnected": 0,
      "giving": 1,
      "taking": 2,
      "mutuality_ratio": 0.6666666666666666,
      "cooperative_pct": 1.0869565217391304,
      "uncooperative_pct": 1.0869565217391304,
      "total_words": 184
    },
    "8": {
      "collective": 1,
      "individual": 0,
      "connected": 0,
      "disconnected": 0,
      "giving": 1,
      "taking": 3,
      "mutuality_ratio": 0.5,
      "cooperative_pct": 1.0638297872340425,
      "uncooperative_pct": 1.5957446808510638,
      "total_words": 188
    },
    "9": {
      "collective": 1,
      "individual": 0,
      "connected": 0,
      "disconnected": 0,
      "giving": 1,
      "taking": 3,
      "mutuality_ratio": 0.5,
      "cooperative_pct": 1.0752688172043012,
      "uncooperative_pct": 1.6129032258064515,
      "total_words": 186
    },
    "10": {
      "collective": 0,
      "individual": 0,
      "connected": 0,
      "disconnected": 0,
      "giving": 0,
      "taking": 4,
      "mutuality_ratio": 0.0,
      "cooperative_pct": 0.0,
      "uncooperative_pct": 2.185792349726776,
      "total_words": 183
    },
    "11": {
      "collective": 1,
      "individual": 0,
      "connected": 0,
      "disconnected": 0,
      "giving": 1,
      "taking": 2,
      "mutuality_ratio": 0.6666666666666666,
      "cooperative_pct": 1.092896174863388,
      "uncooperative_pct": 1.092896174863388,
      "total_words": 183
    },
    "12": {
      "collective": 1,
      "individual": 0,
      "connected": 0,
      "disconnected": 0,
      "giving": 1,
      "taking": 3,
      "mutuality_ratio": 0.5,
      "cooperative_pct": 1.06951871657754,
      "uncooperative_pct": 1.6042780748663104,
      "total_words": 187
    },
    "13": {
      "collective": 1,
      "individual": 0,
      "connected": 0,
      "disconnected": 0,
      "giving": 2,
      "taking": 2,
      "mutuality_ratio": 1.0,
      "cooperative_pct": 1.5957446808510638,
      "uncooperative_pct": 1.0638297872340425,
      "total_words": 188
    },
    "14": {
      "collective": 1,
      "individual": 0,
      "connected": 0,
      "disconnected": 0,
      "giving": 5,
      "taking": 3,
      "mutuality_ratio": 1.5,
      "cooperative_pct": 3.1746031746031744,
      "uncooperative_pct": 1.5873015873015872,
      "total_words": 189
    },
    "15": {
      "collective": 1,
      "individual": 0,
      "connected": 1,
      "disconnected": 0,
      "giving": 1,
      "taking": 3,
      "mutuality_ratio": 0.75,
      "cooperative_pct": 1.5228426395939088,
      "uncooperative_pct": 1.5228426395939088,
      "total_words": 197
    }
  }
}